yliveticker/__init__.py
yliveticker/client_code.py
yliveticker/yaticker_pb2.py
yliveticker_test-0.3.2.dist-info/LICENSE
yliveticker_test-0.3.2.dist-info/METADATA
yliveticker_test-0.3.2.dist-info/WHEEL
yliveticker_test-0.3.2.dist-info/top_level.txt
yliveticker_test-0.3.2.dist-info/RECORD
