Metadata-Version: 2.1
Name: yliveticker-test
Version: 0.3.2
Summary: Live market data from Yahoo! Finance websocket
Home-page: https://github.com/yahoofinancelive/yliveticker
Author: Alexey Paramonov
Author-email: yliveticker@gmail.com
License: UNKNOWN
Platform: UNKNOWN
Classifier: Programming Language :: Python :: 3
Classifier: License :: OSI Approved :: MIT License
Classifier: Operating System :: OS Independent
Requires-Python: >=2.7, !=3.0.*, !=3.1.*, !=3.2.*, !=3.3.*, !=3.4.*
Requires-Dist: protobuf (>=3.11.0)
Requires-Dist: websocket-client (>=0.57.0)
